AUTHORS
CHANGES
LICENSE
MANIFEST.in
README
README.rst
setup.py
django_tracking_jl.egg-info/PKG-INFO
django_tracking_jl.egg-info/SOURCES.txt
django_tracking_jl.egg-info/dependency_links.txt
django_tracking_jl.egg-info/pbr.json
django_tracking_jl.egg-info/top_level.txt
tracking/__init__.py
tracking/__init__.py.bak
tracking/admin.py
tracking/admin.py.bak
tracking/middleware.py
tracking/middleware.py.bak
tracking/models.py
tracking/models.py.bak
tracking/urls.py
tracking/urls.py.bak
tracking/utils.py
tracking/utils.py.bak
tracking/views.py
tracking/views.py.bak
tracking/locale/de/LC_MESSAGES/django.mo
tracking/locale/de/LC_MESSAGES/django.po
tracking/media/tracking/img/Flags.zip
tracking/media/tracking/img/famfamfam_flag_icons.zip
tracking/media/tracking/js/jquery-1.4.4.min.js
tracking/migrations/0001_initial.py
tracking/migrations/__init__.py
tracking/templates/base.html
tracking/templates/tracking/_active_users.html
tracking/templates/tracking/_active_users.js
tracking/templates/tracking/refresh_active_users.js
tracking/templates/tracking/visitor_map.html
tracking/templatetags/__init__.py
tracking/templatetags/tracking_tags.py
tracking/templatetags/tracking_tags.py.bak