Metadata-Version: 1.1
Name: django-tracking-jl
Version: 0.5.7
Summary: Basic visitor tracking and blacklisting for Django
Home-page: https://github.com/jlachowski/django-tracking
Author: Jaroslaw Lachowski
Author-email: jalachowski@gmail.com
License: MIT
Keywords: d,j,a,n,g,o,,, ,t,r,a,c,k,i,n,g,,, ,v,i,s,i,t,o,r,s
Platform: UNKNOWN
Classifier: Development Status :: 5 - Production/Stable
Classifier: Environment :: Web Environment
Classifier: Framework :: Django
Classifier: Intended Audience :: Developers
Classifier: Intended Audience :: Information Technology
Classifier: Intended Audience :: System Administrators
Classifier: License :: OSI Approved :: MIT License
Classifier: Natural Language :: English
Classifier: Operating System :: OS Independent
Classifier: Programming Language :: Python
Classifier: Topic :: Internet :: Log Analysis
Classifier: Topic :: Internet :: WWW/HTTP :: Dynamic Content :: Page Counters
Classifier: Topic :: Internet :: WWW/HTTP :: WSGI :: Middleware
Classifier: Topic :: Security
Classifier: Topic :: System :: Monitoring
Classifier: Topic :: Utilities
